{
  "project_info": {
    "project_number": "654350606220",
    "project_id": "make-it-so-firebase-app-93726",
    "storage_bucket": "make-it-so-firebase-app-93726.firebasestorage.app"
  },
  "client": [
    {
      "client_info": {
        "mobilesdk_app_id": "1:654350606220:android:96dca237d0efb430d640a9",
        "android_client_info": {
          "package_name": "com.example.makeitso"
        }
      },
      "oauth_client": [],
      "api_key": [
        {
          "current_key": "AIzaSyC8qvJ0iof0t-Ig9GPjYj2fLnvbWaM7vS8"
        }
      ],
      "services": {
        "appinvite_service": {
          "other_platform_oauth_client": []
        }
      }
    }
  ],
  "configuration_version": "1"
}